{"buildId":"69af549fe7b09ad7a7c0608d","buildName":"Elf — Winged Striker","scenarioId":"dragon-assault","scenarioName":"Dragon Assault","numRuns":3,"winRate":0,"avgRounds":4.7,"sampleLogs":[{"runIndex":0,"winner":"draw","rounds":10,"bardHpPct":1,"log":["\n══ ROUND 1 ══","\n--- Elf — Winged Striker --- HP: 67/67 | AC: 14","  REASONING: ROUND 1: 1 enemies. Opening with Hypnotic Pattern.","  ACTION: Cast Hypnotic Pattern (Level 3 slot, 2 remaining). DC 16 WIS save. 30ft cube.","    → Young Red Dragon: WIS save [d20:3+4=7 vs DC 16] FAIL!","    → 1/1 targets affected.","\n--- Young Red Dragon --- HP: 178/178 | AC: 18 | Cond: [charmed_hp, incapacitated]","  ** INCAPACITATED ** Cannot take actions.","\n══ ROUND 2 ══","\n--- Elf — Winged Striker --- HP: 67/67 | AC: 14 | Conc: Hypnotic Pattern","  REASONING: All 1 enemies disabled by Hypnotic Pattern. Dodging to maintain concentration.","  ACTION: Dodge. Attacks against have disadvantage.","\n--- Young Red Dragon --- HP: 178/178 | AC: 18 | Cond: [charmed_hp, incapacitated]","  ** INCAPACITATED ** Cannot take actions.","\n══ ROUND 3 ══","\n--- Elf — Winged Striker --- HP: 67/67 | AC: 14 | Conc: Hypnotic Pattern","  REASONING: All 1 enemies disabled by Hypnotic Pattern. Dodging to maintain concentration.","  ACTION: Dodge. Attacks against have disadvantage.","\n--- Young Red Dragon --- HP: 178/178 | AC: 18 | Cond: [charmed_hp, incapacitated]","  ** INCAPACITATED ** Cannot take actions.","\n══ ROUND 4 ══","\n--- Elf — Winged Striker --- HP: 67/67 | AC: 14 | Conc: Hypnotic Pattern","  REASONING: All 1 enemies disabled by Hypnotic Pattern. Dodging to maintain concentration.","  ACTION: Dodge. Attacks against have disadvantage.","\n--- Young Red Dragon --- HP: 178/178 | AC: 18 | Cond: [charmed_hp, incapacitated]","  ** INCAPACITATED ** Cannot take actions.","\n══ ROUND 5 ══","\n--- Elf — Winged Striker --- HP: 67/67 | AC: 14 | Conc: Hypnotic Pattern","  REASONING: All 1 enemies disabled by Hypnotic Pattern. Dodging to maintain concentration.","  ACTION: Dodge. Attacks against have disadvantage.","\n--- Young Red Dragon --- HP: 178/178 | AC: 18 | Cond: [charmed_hp, incapacitated]","  ** INCAPACITATED ** Cannot take actions.","\n══ ROUND 6 ══","\n--- Elf — Winged Striker --- HP: 67/67 | AC: 14 | Conc: Hypnotic Pattern","  REASONING: All 1 enemies disabled by Hypnotic Pattern. Dodging to maintain concentration.","  ACTION: Dodge. Attacks against have disadvantage.","\n--- Young Red Dragon --- HP: 178/178 | AC: 18 | Cond: [charmed_hp, incapacitated]","  ** INCAPACITATED ** Cannot take actions.","\n══ ROUND 7 ══","\n--- Elf — Winged Striker --- HP: 67/67 | AC: 14 | Conc: Hypnotic Pattern","  REASONING: All 1 enemies disabled by Hypnotic Pattern. Dodging to maintain concentration.","  ACTION: Dodge. Attacks against have disadvantage.","\n--- Young Red Dragon --- HP: 178/178 | AC: 18 | Cond: [charmed_hp, incapacitated]","  ** INCAPACITATED ** Cannot take actions.","\n══ ROUND 8 ══","\n--- Elf — Winged Striker --- HP: 67/67 | AC: 14 | Conc: Hypnotic Pattern","  REASONING: All 1 enemies disabled by Hypnotic Pattern. Dodging to maintain concentration.","  ACTION: Dodge. Attacks against have disadvantage.","\n--- Young Red Dragon --- HP: 178/178 | AC: 18 | Cond: [charmed_hp, incapacitated]","  ** INCAPACITATED ** Cannot take actions.","\n══ ROUND 9 ══","\n--- Elf — Winged Striker --- HP: 67/67 | AC: 14 | Conc: Hypnotic Pattern","  REASONING: All 1 enemies disabled by Hypnotic Pattern. Dodging to maintain concentration.","  ACTION: Dodge. Attacks against have disadvantage.","\n--- Young Red Dragon --- HP: 178/178 | AC: 18 | Cond: [charmed_hp, incapacitated]","  ** INCAPACITATED ** Cannot take actions.","\n══ ROUND 10 ══","\n--- Elf — Winged Striker --- HP: 67/67 | AC: 14 | Conc: Hypnotic Pattern","  REASONING: All 1 enemies disabled by Hypnotic Pattern. Dodging to maintain concentration.","  ACTION: Dodge. Attacks against have disadvantage."],"analytics":[{"name":"Elf — Winged Striker","side":"party","finalHP":67,"maxHP":67,"alive":true,"damageDealt":0,"damageTaken":0,"attacksMade":0,"attacksHit":0,"hitRate":0,"spellsCast":1,"concentrationSaves":{"made":0,"failed":0},"conditionsInflicted":2,"conditions":["dodging"]},{"name":"Young Red Dragon","side":"enemy","finalHP":178,"maxHP":178,"alive":true,"damageDealt":0,"damageTaken":0,"attacksMade":0,"attacksHit":0,"hitRate":0,"spellsCast":0,"concentrationSaves":{"made":0,"failed":0},"conditionsInflicted":0,"conditions":["charmed_hp","incapacitated"]}]},{"runIndex":1,"winner":"enemy","rounds":2,"bardHpPct":0,"log":["\n══ ROUND 1 ══","\n--- Young Red Dragon --- HP: 178/178 | AC: 18","  REASONING: Multiattack on Elf — Winged Striker (3 attacks).","  ACTION: Multiattack (3× Bite) on Elf — Winged Striker","    → Bite: [d20:14+10=24 vs AC 14] HIT! 15 damage. Elf — Winged Striker HP: 52/67","    → Bite: [d20:16+10=26 vs AC 14] HIT! 17 damage. Elf — Winged Striker HP: 35/67","    → Bite: [d20:4+10=14 vs AC 14] HIT! 24 damage. Elf — Winged Striker HP: 11/67","\n--- Elf — Winged Striker --- HP: 11/67 | AC: 14","  REASONING: HP CRITICAL (11/67). Going invisible for survival.","  ACTION: Cast Greater Invisibility (Level 4 slot, 1 remaining).","    → Elf — Winged Striker is affected by Greater Invisibility.","\n══ ROUND 2 ══","\n--- Young Red Dragon --- HP: 178/178 | AC: 18","  REASONING: Multiattack on Elf — Winged Striker (3 attacks).","  ACTION: Multiattack (3× Bite) on Elf — Winged Striker","    → Bite: [d20:2+10=12 vs AC 14] MISS.","    → Bite: [d20:11+10=21 vs AC 14] HIT! 16 damage. Elf — Winged Striker HP: -5/67","    → Concentration save: [d20:10+4=14 vs DC 10] MAINTAINED!"],"analytics":[{"name":"Elf — Winged Striker","side":"party","finalHP":0,"maxHP":67,"alive":false,"damageDealt":0,"damageTaken":72,"attacksMade":0,"attacksHit":0,"hitRate":0,"spellsCast":1,"concentrationSaves":{"made":1,"failed":0},"conditionsInflicted":0,"conditions":["invisible"]},{"name":"Young Red Dragon","side":"enemy","finalHP":178,"maxHP":178,"alive":true,"damageDealt":72,"damageTaken":0,"attacksMade":5,"attacksHit":4,"hitRate":80,"spellsCast":0,"concentrationSaves":{"made":0,"failed":0},"conditionsInflicted":0,"conditions":[]}]},{"runIndex":2,"winner":"enemy","rounds":2,"bardHpPct":0,"log":["\n══ ROUND 1 ══","\n--- Young Red Dragon --- HP: 178/178 | AC: 18","  REASONING: Multiattack on Elf — Winged Striker (3 attacks).","  ACTION: Multiattack (3× Bite) on Elf — Winged Striker","    → Bite: [d20:14+10=24 vs AC 14] HIT! 20 damage. Elf — Winged Striker HP: 47/67","    → Bite: [d20:20+10=30 vs AC 14] CRITICAL HIT! 30 damage. Elf — Winged Striker HP: 17/67","    → Bite: [d20:1+10=11 vs AC 14] MISS.","\n--- Elf — Winged Striker --- HP: 17/67 | AC: 14","  REASONING: ROUND 1: 1 enemies. Opening with Hypnotic Pattern.","  ACTION: Cast Hypnotic Pattern (Level 3 slot, 2 remaining). DC 16 WIS save. 30ft cube.","    → Young Red Dragon: WIS save [d20:16+4=20 vs DC 16] SUCCESS. Resists.","    → No targets affected. Spell wasted.","\n══ ROUND 2 ══","\n--- Young Red Dragon --- HP: 178/178 | AC: 18","  REASONING: Multiattack on Elf — Winged Striker (3 attacks).","  ACTION: Multiattack (3× Bite) on Elf — Winged Striker","    → Bite: [d20:8+10=18 vs AC 14] HIT! 21 damage. Elf — Winged Striker HP: -4/67"],"analytics":[{"name":"Elf — Winged Striker","side":"party","finalHP":0,"maxHP":67,"alive":false,"damageDealt":0,"damageTaken":71,"attacksMade":0,"attacksHit":0,"hitRate":0,"spellsCast":1,"concentrationSaves":{"made":0,"failed":0},"conditionsInflicted":0,"conditions":[]},{"name":"Young Red Dragon","side":"enemy","finalHP":178,"maxHP":178,"alive":true,"damageDealt":71,"damageTaken":0,"attacksMade":4,"attacksHit":3,"hitRate":75,"spellsCast":0,"concentrationSaves":{"made":0,"failed":0},"conditionsInflicted":0,"conditions":[]}]}]}