{"engine":"v2","buildId":"69af549fe7b09ad7a7c057ef","buildName":"Thri-kreen — Bardic Musician","scenarioId":"lich-encounter","scenarioName":"Lich Encounter","numRuns":100,"winRate":0.24,"avgRounds":8.2,"sampleLogs":[{"runIndex":0,"winner":"enemy","rounds":5,"bardHpPct":0,"log":["=== INITIATIVE ===","  Lich: 20 (d20:17 + 3)","  Thri-kreen — Bardic Musician: 4 (d20:2 + 2)","\n=== ROUND 1 ===","\n  --- Lich's turn ---","  ⚡ Thri-kreen — Bardic Musician casts Counterspell (3rd level)! Power Word Stun is COUNTERED!","\n  --- Thri-kreen — Bardic Musician's turn ---","Thri-kreen — Bardic Musician casts Hypnotic Pattern (3rd level)","  → AoE hits 1 target(s)","  → Lich WIS save: SUCCESS","\n=== ROUND 2 ===","\n  --- Lich's turn ---","Lich casts Finger of Death (7th level)","  → Thri-kreen — Bardic Musician CON save: [22 vs DC 20] SUCCESS!","    → Half damage: 30","    → Concentration save: [17 vs DC 15] MAINTAINED!","  ⚡ Thri-kreen — Bardic Musician tries Counterspell but fails the check!","\n  --- Thri-kreen — Bardic Musician's turn ---","Thri-kreen — Bardic Musician casts Dissonant Whispers (1st level)","  → Lich WIS save: [19 vs DC 16] SUCCESS! (advantage)","    → Half damage: 6","Thri-kreen — Bardic Musician casts Healing Word (1st level)","  → Heals Thri-kreen — Bardic Musician for 8. HP: 45/67","\n=== ROUND 3 ===","\n  --- Lich's turn ---","Lich casts Fireball (3rd level)","  → AoE hits 1 target(s)","  → Thri-kreen — Bardic Musician DEX save: FAIL","    → Concentration save: [22 vs DC 10] MAINTAINED!","\n  --- Thri-kreen — Bardic Musician's turn ---","Thri-kreen — Bardic Musician casts Dissonant Whispers (1st level)","  → Lich WIS save: [24 vs DC 16] SUCCESS! (advantage)","    → Half damage: 7","Thri-kreen — Bardic Musician casts Healing Word (1st level)","  → Heals Thri-kreen — Bardic Musician for 9. HP: 33/67","\n=== ROUND 4 ===","\n  --- Lich's turn ---","Lich casts Fireball (3rd level)","  → AoE hits 1 target(s)","  → Thri-kreen — Bardic Musician DEX save: FAIL","    → Concentration save: [20 vs DC 10] MAINTAINED!","\n  --- Thri-kreen — Bardic Musician's turn ---","Thri-kreen — Bardic Musician casts Greater Invisibility (4th level)","  → Thri-kreen — Bardic Musician loses concentration on Hypnotic Pattern","\n=== ROUND 5 ===","\n  --- Lich's turn ---","Lich casts Fireball (3rd level)","  → AoE hits 1 target(s)","  → Thri-kreen — Bardic Musician DEX save: FAIL","\n=== ENCOUNTER ENDED — Winner: ENEMY after 5 rounds ==="],"analytics":[{"id":"bard-0","name":"Thri-kreen — Bardic Musician","side":"party","survived":false,"finalHP":0,"maxHP":67,"damageDealt":13,"damageTaken":98,"attacksMade":0,"attacksHit":0,"hitRate":0,"spellsCast":8},{"id":"lich-0","name":"Lich","side":"enemy","survived":true,"finalHP":122,"maxHP":135,"damageDealt":98,"damageTaken":13,"attacksMade":0,"attacksHit":0,"hitRate":0,"spellsCast":5}],"positionSnapshots":[{"round":0,"phase":"start","combatants":[{"id":"bard-0","name":"Thri-kreen — Bardic Musician","side":"party","currentHP":67,"maxHP":67,"conditions":[],"position":{"x":0,"y":0},"flying":false},{"id":"lich-0","name":"Lich","side":"enemy","currentHP":135,"maxHP":135,"conditions":[],"position":{"x":8,"y":0},"flying":false}]},{"round":1,"phase":"end","combatants":[{"id":"bard-0","name":"Thri-kreen — Bardic Musician","side":"party","currentHP":67,"maxHP":67,"conditions":[],"position":{"x":0,"y":0},"flying":false},{"id":"lich-0","name":"Lich","side":"enemy","currentHP":135,"maxHP":135,"conditions":[],"position":{"x":8,"y":0},"flying":false}]},{"round":2,"phase":"end","combatants":[{"id":"bard-0","name":"Thri-kreen — Bardic Musician","side":"party","currentHP":45,"maxHP":67,"conditions":[],"position":{"x":0,"y":0},"flying":false},{"id":"lich-0","name":"Lich","side":"enemy","currentHP":129,"maxHP":135,"conditions":[],"position":{"x":8,"y":0},"flying":false}]},{"round":3,"phase":"end","combatants":[{"id":"bard-0","name":"Thri-kreen — Bardic Musician","side":"party","currentHP":33,"maxHP":67,"conditions":[],"position":{"x":0,"y":0},"flying":false},{"id":"lich-0","name":"Lich","side":"enemy","currentHP":122,"maxHP":135,"conditions":[],"position":{"x":8,"y":0},"flying":false}]},{"round":4,"phase":"end","combatants":[{"id":"bard-0","name":"Thri-kreen — Bardic Musician","side":"party","currentHP":12,"maxHP":67,"conditions":[],"position":{"x":0,"y":0},"flying":false},{"id":"lich-0","name":"Lich","side":"enemy","currentHP":122,"maxHP":135,"conditions":[],"position":{"x":8,"y":0},"flying":false}]},{"round":5,"phase":"end","combatants":[{"id":"bard-0","name":"Thri-kreen — Bardic Musician","side":"party","currentHP":0,"maxHP":67,"conditions":[],"position":{"x":0,"y":0},"flying":false},{"id":"lich-0","name":"Lich","side":"enemy","currentHP":122,"maxHP":135,"conditions":[],"position":{"x":8,"y":0},"flying":false}]}]},{"runIndex":1,"winner":"party","rounds":12,"bardHpPct":1,"log":["=== INITIATIVE ===","  Thri-kreen — Bardic Musician: 17 (d20:15 + 2)","  Lich: 13 (d20:10 + 3)","\n=== ROUND 1 ===","\n  --- Thri-kreen — Bardic Musician's turn ---","Thri-kreen — Bardic Musician casts Hypnotic Pattern (3rd level)","  → AoE hits 1 target(s)","  → Lich WIS save: SUCCESS","\n  --- Lich's turn ---","Lich casts Power Word Stun (8th level)","  ⚡ Thri-kreen — Bardic Musician tries Counterspell but fails the check!","\n=== ROUND 2 ===","\n  --- Thri-kreen — Bardic Musician's turn ---","Thri-kreen — Bardic Musician casts Dissonant Whispers (1st level)","  → Lich WIS save: [27 vs DC 16] SUCCESS! (advantage)","    → Half damage: 8","\n  --- Lich's turn ---","  ⚡ Thri-kreen — Bardic Musician casts Counterspell (3rd level)! Finger of Death is COUNTERED!","\n=== ROUND 3 ===","\n  --- Thri-kreen — Bardic Musician's turn ---","Thri-kreen — Bardic Musician casts Dissonant Whispers (1st level)","  → Lich WIS save: [20 vs DC 16] SUCCESS! (advantage)","    → Half damage: 4","\n  --- Lich's turn ---","Lich casts Fireball (3rd level)","  → AoE hits 1 target(s)","  → Thri-kreen — Bardic Musician DEX save: SUCCESS","    → Concentration save: [18 vs DC 10] MAINTAINED!","\n=== ROUND 4 ===","\n  --- Thri-kreen — Bardic Musician's turn ---","Thri-kreen — Bardic Musician casts Dissonant Whispers (1st level)","  → Lich WIS save: [27 vs DC 16] SUCCESS! (advantage)","    → Half damage: 4","\n  --- Lich's turn ---","Lich casts Fireball (3rd level)","  → AoE hits 1 target(s)","  → Thri-kreen — Bardic Musician DEX save: FAIL","  → Thri-kreen — Bardic Musician loses concentration on Hypnotic Pattern","\n=== ROUND 5 ===","\n  --- Thri-kreen — Bardic Musician's turn ---","Thri-kreen — Bardic Musician casts Polymorph (4th level)","  → Thri-kreen — Bardic Musician polymorphs into a Giant Ape! (157 HP, AC 12, multiattack: 2)","Bonus action error: Invalid choice: Option not available: bonus-1","\n  --- Lich's turn ---","Lich casts Fireball (3rd level)","  → AoE hits 1 target(s)","  → Thri-kreen — Bardic Musician DEX save: FAIL","  → Thri-kreen — Bardic Musician loses concentration on Polymorph","  → Thri-kreen — Bardic Musician reverts from Polymorph to original form (HP: 28/67)","\n=== ROUND 6 ===","\n  --- Thri-kreen — Bardic Musician's turn ---","Thri-kreen — Bardic Musician casts Polymorph (4th level)","  → Thri-kreen — Bardic Musician polymorphs into a Giant Ape! (157 HP, AC 12, multiattack: 2)","Bonus action error: Invalid choice: Option not available: bonus-1","\n  --- Lich's turn ---","Lich takes the Dodge action.","\n=== ROUND 7 ===","\n  --- Thri-kreen — Bardic Musician's turn ---","Thri-kreen — Bardic Musician moves from (0,0) to (8,0) [40ft].","  Thri-kreen — Bardic Musician attack 1: [d20:5+9=14 vs AC 17] MISS!","  Thri-kreen — Bardic Musician attack 2: [d20:2+9=11 vs AC 17] MISS!","\n  --- Lich's turn ---","Lich takes the Dodge action.","\n=== ROUND 8 ===","\n  --- Thri-kreen — Bardic Musician's turn ---","  Thri-kreen — Bardic Musician attack 1: [d20:8+9=17 vs AC 17] HIT! 28 damage. Lich HP: 91/135","  Thri-kreen — Bardic Musician attack 2: [d20:2+9=11 vs AC 17] MISS!","\n  --- Lich's turn ---","Lich takes the Dodge action.","\n=== ROUND 9 ===","\n  --- Thri-kreen — Bardic Musician's turn ---","  Thri-kreen — Bardic Musician attack 1: [d20:9+9=18 vs AC 17] HIT! 23 damage. Lich HP: 68/135","  Thri-kreen — Bardic Musician attack 2: [d20:7+9=16 vs AC 17] MISS!","\n  --- Lich's turn ---","Lich takes the Dodge action.","\n=== ROUND 10 ===","\n  --- Thri-kreen — Bardic Musician's turn ---","  Thri-kreen — Bardic Musician attack 1: [d20:3+9=12 vs AC 17] MISS!","  Thri-kreen — Bardic Musician attack 2: [d20:15+9=24 vs AC 17] HIT! 15 damage. Lich HP: 53/135","\n  --- Lich's turn ---","Lich takes the Dodge action.","\n=== ROUND 11 ===","\n  --- Thri-kreen — Bardic Musician's turn ---","  Thri-kreen — Bardic Musician attack 1: [d20:13+9=22 vs AC 17] HIT! 19 damage. Lich HP: 34/135","  Thri-kreen — Bardic Musician attack 2: [d20:2+9=11 vs AC 17] MISS!","\n  --- Lich's turn ---","Lich takes the Dodge action.","\n=== ROUND 12 ===","\n  --- Thri-kreen — Bardic Musician's turn ---","  Thri-kreen — Bardic Musician attack 1: [d20:18+9=27 vs AC 17] HIT! 24 damage. Lich HP: 10/135","  Thri-kreen — Bardic Musician attack 2: [d20:12+9=21 vs AC 17] HIT! 18 damage. Lich HP: 0/135","\n=== ENCOUNTER ENDED — Winner: PARTY after 12 rounds ==="],"analytics":[{"id":"bard-0","name":"Thri-kreen — Bardic Musician","side":"party","survived":true,"finalHP":157,"maxHP":157,"damageDealt":143,"damageTaken":68,"attacksMade":12,"attacksHit":6,"hitRate":50,"spellsCast":8},{"id":"lich-0","name":"Lich","side":"enemy","survived":false,"finalHP":0,"maxHP":135,"damageDealt":68,"damageTaken":143,"attacksMade":0,"attacksHit":0,"hitRate":0,"spellsCast":5}],"positionSnapshots":[{"round":0,"phase":"start","combatants":[{"id":"bard-0","name":"Thri-kreen — Bardic Musician","side":"party","currentHP":67,"maxHP":67,"conditions":[],"position":{"x":0,"y":0},"flying":false},{"id":"lich-0","name":"Lich","side":"enemy","currentHP":135,"maxHP":135,"conditions":[],"position":{"x":8,"y":0},"flying":false}]},{"round":1,"phase":"end","combatants":[{"id":"bard-0","name":"Thri-kreen — Bardic Musician","side":"party","currentHP":67,"maxHP":67,"conditions":[],"position":{"x":0,"y":0},"flying":false},{"id":"lich-0","name":"Lich","side":"enemy","currentHP":135,"maxHP":135,"conditions":[],"position":{"x":8,"y":0},"flying":false}]},{"round":2,"phase":"end","combatants":[{"id":"bard-0","name":"Thri-kreen — Bardic Musician","side":"party","currentHP":67,"maxHP":67,"conditions":[],"position":{"x":0,"y":0},"flying":false},{"id":"lich-0","name":"Lich","side":"enemy","currentHP":127,"maxHP":135,"conditions":[],"position":{"x":8,"y":0},"flying":false}]},{"round":3,"phase":"end","combatants":[{"id":"bard-0","name":"Thri-kreen — Bardic Musician","side":"party","currentHP":55,"maxHP":67,"conditions":[],"position":{"x":0,"y":0},"flying":false},{"id":"lich-0","name":"Lich","side":"enemy","currentHP":123,"maxHP":135,"conditions":[],"position":{"x":8,"y":0},"flying":false}]},{"round":4,"phase":"end","combatants":[{"id":"bard-0","name":"Thri-kreen — Bardic Musician","side":"party","currentHP":28,"maxHP":67,"conditions":[],"position":{"x":0,"y":0},"flying":false},{"id":"lich-0","name":"Lich","side":"enemy","currentHP":119,"maxHP":135,"conditions":[],"position":{"x":8,"y":0},"flying":false}]},{"round":5,"phase":"end","combatants":[{"id":"bard-0","name":"Thri-kreen — Bardic Musician","side":"party","currentHP":28,"maxHP":67,"conditions":[],"position":{"x":0,"y":0},"flying":false},{"id":"lich-0","name":"Lich","side":"enemy","currentHP":119,"maxHP":135,"conditions":[],"position":{"x":8,"y":0},"flying":false}]},{"round":6,"phase":"end","combatants":[{"id":"bard-0","name":"Thri-kreen — Bardic Musician","side":"party","currentHP":157,"maxHP":157,"conditions":["polymorphed"],"position":{"x":0,"y":0},"flying":false},{"id":"lich-0","name":"Lich","side":"enemy","currentHP":119,"maxHP":135,"conditions":["dodging"],"position":{"x":8,"y":0},"flying":false}]},{"round":7,"phase":"end","combatants":[{"id":"bard-0","name":"Thri-kreen — Bardic Musician","side":"party","currentHP":157,"maxHP":157,"conditions":["polymorphed"],"position":{"x":8,"y":0},"flying":false},{"id":"lich-0","name":"Lich","side":"enemy","currentHP":119,"maxHP":135,"conditions":["dodging"],"position":{"x":8,"y":0},"flying":false}]},{"round":8,"phase":"end","combatants":[{"id":"bard-0","name":"Thri-kreen — Bardic Musician","side":"party","currentHP":157,"maxHP":157,"conditions":["polymorphed"],"position":{"x":8,"y":0},"flying":false},{"id":"lich-0","name":"Lich","side":"enemy","currentHP":91,"maxHP":135,"conditions":["dodging"],"position":{"x":8,"y":0},"flying":false}]},{"round":9,"phase":"end","combatants":[{"id":"bard-0","name":"Thri-kreen — Bardic Musician","side":"party","currentHP":157,"maxHP":157,"conditions":["polymorphed"],"position":{"x":8,"y":0},"flying":false},{"id":"lich-0","name":"Lich","side":"enemy","currentHP":68,"maxHP":135,"conditions":["dodging"],"position":{"x":8,"y":0},"flying":false}]},{"round":10,"phase":"end","combatants":[{"id":"bard-0","name":"Thri-kreen — Bardic Musician","side":"party","currentHP":157,"maxHP":157,"conditions":["polymorphed"],"position":{"x":8,"y":0},"flying":false},{"id":"lich-0","name":"Lich","side":"enemy","currentHP":53,"maxHP":135,"conditions":["dodging"],"position":{"x":8,"y":0},"flying":false}]},{"round":11,"phase":"end","combatants":[{"id":"bard-0","name":"Thri-kreen — Bardic Musician","side":"party","currentHP":157,"maxHP":157,"conditions":["polymorphed"],"position":{"x":8,"y":0},"flying":false},{"id":"lich-0","name":"Lich","side":"enemy","currentHP":34,"maxHP":135,"conditions":["dodging"],"position":{"x":8,"y":0},"flying":false}]},{"round":12,"phase":"end","combatants":[{"id":"bard-0","name":"Thri-kreen — Bardic Musician","side":"party","currentHP":157,"maxHP":157,"conditions":["polymorphed"],"position":{"x":8,"y":0},"flying":false},{"id":"lich-0","name":"Lich","side":"enemy","currentHP":0,"maxHP":135,"conditions":["dodging"],"position":{"x":8,"y":0},"flying":false}]}]},{"runIndex":2,"winner":"party","rounds":10,"bardHpPct":1,"log":["=== INITIATIVE ===","  Lich: 13 (d20:10 + 3)","  Thri-kreen — Bardic Musician: 3 (d20:1 + 2)","\n=== ROUND 1 ===","\n  --- Lich's turn ---","  ⚡ Thri-kreen — Bardic Musician casts Counterspell (3rd level)! Power Word Stun is COUNTERED!","\n  --- Thri-kreen — Bardic Musician's turn ---","Thri-kreen — Bardic Musician casts Hypnotic Pattern (3rd level)","  → AoE hits 1 target(s)","  → Lich WIS save: SUCCESS","\n=== ROUND 2 ===","\n  --- Lich's turn ---","  ⚡ Thri-kreen — Bardic Musician casts Counterspell (3rd level)! Finger of Death is COUNTERED!","\n  --- Thri-kreen — Bardic Musician's turn ---","Thri-kreen — Bardic Musician casts Dissonant Whispers (1st level)","    → Lich uses Legendary Resistance! (2 remaining)","  → Lich WIS save: [15 vs DC 16] SUCCESS (Legendary Resistance)","    → Half damage: 5","\n=== ROUND 3 ===","\n  --- Lich's turn ---","Lich casts Fireball (3rd level)","  → AoE hits 1 target(s)","  → Thri-kreen — Bardic Musician DEX save: SUCCESS","    → Concentration save: [19 vs DC 10] MAINTAINED!","\n  --- Thri-kreen — Bardic Musician's turn ---","Thri-kreen — Bardic Musician casts Dissonant Whispers (1st level)","    → Lich uses Legendary Resistance! (1 remaining)","  → Lich WIS save: [15 vs DC 16] SUCCESS (Legendary Resistance)","    → Half damage: 6","\n=== ROUND 4 ===","\n  --- Lich's turn ---","Lich casts Fireball (3rd level)","  → AoE hits 1 target(s)","  → Thri-kreen — Bardic Musician DEX save: SUCCESS","  → Thri-kreen — Bardic Musician loses concentration on Hypnotic Pattern","\n  --- Thri-kreen — Bardic Musician's turn ---","Thri-kreen — Bardic Musician casts Polymorph (4th level)","  → Thri-kreen — Bardic Musician polymorphs into a Giant Ape! (157 HP, AC 12, multiattack: 2)","Bonus action error: Invalid choice: Option not available: bonus-1","\n=== ROUND 5 ===","\n  --- Lich's turn ---","Lich casts Fireball (3rd level)","  → AoE hits 1 target(s)","  → Thri-kreen — Bardic Musician DEX save: FAIL","  → Thri-kreen — Bardic Musician loses concentration on Polymorph","  → Thri-kreen — Bardic Musician reverts from Polymorph to original form (HP: 38/67)","\n  --- Thri-kreen — Bardic Musician's turn ---","Thri-kreen — Bardic Musician casts Polymorph (4th level)","  → Thri-kreen — Bardic Musician polymorphs into a Giant Ape! (157 HP, AC 12, multiattack: 2)","Bonus action error: Invalid choice: Option not available: bonus-1","\n=== ROUND 6 ===","\n  --- Lich's turn ---","Lich takes the Dodge action.","\n  --- Thri-kreen — Bardic Musician's turn ---","Thri-kreen — Bardic Musician moves from (0,0) to (8,0) [40ft].","  Thri-kreen — Bardic Musician attack 1: [d20:10+9=19 vs AC 17] HIT! 20 damage. Lich HP: 104/135","  Thri-kreen — Bardic Musician attack 2: [d20:16+9=25 vs AC 17] HIT! 27 damage. Lich HP: 77/135","\n=== ROUND 7 ===","\n  --- Lich's turn ---","Lich takes the Dodge action.","\n  --- Thri-kreen — Bardic Musician's turn ---","  Thri-kreen — Bardic Musician attack 1: [d20:12+9=21 vs AC 17] HIT! 22 damage. Lich HP: 55/135","  Thri-kreen — Bardic Musician attack 2: [d20:6+9=15 vs AC 17] MISS!","\n=== ROUND 8 ===","\n  --- Lich's turn ---","Lich takes the Dodge action.","\n  --- Thri-kreen — Bardic Musician's turn ---","  Thri-kreen — Bardic Musician attack 1: [d20:13+9=22 vs AC 17] HIT! 27 damage. Lich HP: 28/135","  Thri-kreen — Bardic Musician attack 2: [d20:8+9=17 vs AC 17] HIT! 22 damage. Lich HP: 6/135","\n=== ROUND 9 ===","\n  --- Lich's turn ---","Lich takes the Dodge action.","\n  --- Thri-kreen — Bardic Musician's turn ---","  Thri-kreen — Bardic Musician attack 1: [d20:3+9=12 vs AC 17] MISS!","  Thri-kreen — Bardic Musician attack 2: [d20:4+9=13 vs AC 17] MISS!","\n=== ROUND 10 ===","\n  --- Lich's turn ---","Lich takes the Dodge action.","\n  --- Thri-kreen — Bardic Musician's turn ---","  Thri-kreen — Bardic Musician attack 1: [d20:1+9=10 vs AC 17] MISS!","  Thri-kreen — Bardic Musician attack 2: [d20:14+9=23 vs AC 17] HIT! 21 damage. Lich HP: 0/135","\n=== ENCOUNTER ENDED — Winner: PARTY after 10 rounds ==="],"analytics":[{"id":"bard-0","name":"Thri-kreen — Bardic Musician","side":"party","survived":true,"finalHP":157,"maxHP":157,"damageDealt":150,"damageTaken":55,"attacksMade":10,"attacksHit":6,"hitRate":60,"spellsCast":7},{"id":"lich-0","name":"Lich","side":"enemy","survived":false,"finalHP":0,"maxHP":135,"damageDealt":55,"damageTaken":150,"attacksMade":0,"attacksHit":0,"hitRate":0,"spellsCast":5}],"positionSnapshots":[{"round":0,"phase":"start","combatants":[{"id":"bard-0","name":"Thri-kreen — Bardic Musician","side":"party","currentHP":67,"maxHP":67,"conditions":[],"position":{"x":0,"y":0},"flying":false},{"id":"lich-0","name":"Lich","side":"enemy","currentHP":135,"maxHP":135,"conditions":[],"position":{"x":8,"y":0},"flying":false}]},{"round":1,"phase":"end","combatants":[{"id":"bard-0","name":"Thri-kreen — Bardic Musician","side":"party","currentHP":67,"maxHP":67,"conditions":[],"position":{"x":0,"y":0},"flying":false},{"id":"lich-0","name":"Lich","side":"enemy","currentHP":135,"maxHP":135,"conditions":[],"position":{"x":8,"y":0},"flying":false}]},{"round":2,"phase":"end","combatants":[{"id":"bard-0","name":"Thri-kreen — Bardic Musician","side":"party","currentHP":67,"maxHP":67,"conditions":[],"position":{"x":0,"y":0},"flying":false},{"id":"lich-0","name":"Lich","side":"enemy","currentHP":130,"maxHP":135,"conditions":[],"position":{"x":8,"y":0},"flying":false}]},{"round":3,"phase":"end","combatants":[{"id":"bard-0","name":"Thri-kreen — Bardic Musician","side":"party","currentHP":52,"maxHP":67,"conditions":[],"position":{"x":0,"y":0},"flying":false},{"id":"lich-0","name":"Lich","side":"enemy","currentHP":124,"maxHP":135,"conditions":[],"position":{"x":8,"y":0},"flying":false}]},{"round":4,"phase":"end","combatants":[{"id":"bard-0","name":"Thri-kreen — Bardic Musician","side":"party","currentHP":157,"maxHP":157,"conditions":["polymorphed"],"position":{"x":0,"y":0},"flying":false},{"id":"lich-0","name":"Lich","side":"enemy","currentHP":124,"maxHP":135,"conditions":[],"position":{"x":8,"y":0},"flying":false}]},{"round":5,"phase":"end","combatants":[{"id":"bard-0","name":"Thri-kreen — Bardic Musician","side":"party","currentHP":157,"maxHP":157,"conditions":["polymorphed"],"position":{"x":0,"y":0},"flying":false},{"id":"lich-0","name":"Lich","side":"enemy","currentHP":124,"maxHP":135,"conditions":[],"position":{"x":8,"y":0},"flying":false}]},{"round":6,"phase":"end","combatants":[{"id":"bard-0","name":"Thri-kreen — Bardic Musician","side":"party","currentHP":157,"maxHP":157,"conditions":["polymorphed"],"position":{"x":8,"y":0},"flying":false},{"id":"lich-0","name":"Lich","side":"enemy","currentHP":77,"maxHP":135,"conditions":["dodging"],"position":{"x":8,"y":0},"flying":false}]},{"round":7,"phase":"end","combatants":[{"id":"bard-0","name":"Thri-kreen — Bardic Musician","side":"party","currentHP":157,"maxHP":157,"conditions":["polymorphed"],"position":{"x":8,"y":0},"flying":false},{"id":"lich-0","name":"Lich","side":"enemy","currentHP":55,"maxHP":135,"conditions":["dodging"],"position":{"x":8,"y":0},"flying":false}]},{"round":8,"phase":"end","combatants":[{"id":"bard-0","name":"Thri-kreen — Bardic Musician","side":"party","currentHP":157,"maxHP":157,"conditions":["polymorphed"],"position":{"x":8,"y":0},"flying":false},{"id":"lich-0","name":"Lich","side":"enemy","currentHP":6,"maxHP":135,"conditions":["dodging"],"position":{"x":8,"y":0},"flying":false}]},{"round":9,"phase":"end","combatants":[{"id":"bard-0","name":"Thri-kreen — Bardic Musician","side":"party","currentHP":157,"maxHP":157,"conditions":["polymorphed"],"position":{"x":8,"y":0},"flying":false},{"id":"lich-0","name":"Lich","side":"enemy","currentHP":6,"maxHP":135,"conditions":["dodging"],"position":{"x":8,"y":0},"flying":false}]},{"round":10,"phase":"end","combatants":[{"id":"bard-0","name":"Thri-kreen — Bardic Musician","side":"party","currentHP":157,"maxHP":157,"conditions":["polymorphed"],"position":{"x":8,"y":0},"flying":false},{"id":"lich-0","name":"Lich","side":"enemy","currentHP":0,"maxHP":135,"conditions":["dodging"],"position":{"x":8,"y":0},"flying":false}]}]}]}